microwave_usb_fan_fork/__init__.py
microwave_usb_fan_fork/__main__.py
microwave_usb_fan_fork/fanusb.py
microwave_usb_fan_fork/message.py
microwave_usb_fan_fork/protocol.py
microwave_usb_fan_fork/fonts/Hack-Regular.ttf
microwave_usb_fan_fork/fonts/__init__.py
microwave_usb_fan_fork/resources/__init__.py
microwave_usb_fan_fork/resources/example.res
microwave_usb_fan_fork-0.0.1.dist-info/METADATA
microwave_usb_fan_fork-0.0.1.dist-info/WHEEL
microwave_usb_fan_fork-0.0.1.dist-info/entry_points.txt
microwave_usb_fan_fork-0.0.1.dist-info/licenses/LICENSE
microwave_usb_fan_fork-0.0.1.dist-info/RECORD
