Metadata-Version: 2.4
Name: microwave_usb_fan_fork
Version: 0.0.1
Summary: Rebranded UF-211-06RGB USB fans by USTAR (Ruishengda) protocol implementation
Project-URL: Homepage, https://sourceforge.net/p/ratisbona-fan-fork
Project-URL: Bug Tracker, https://sourceforge.net/p/ratisbona-fan-fork
Author-email: Fergus Symon <45412+fergofrog@users.noreply.github.com>, Ulrich Schwenk <ulrich-schwenk@gmx.de>
Maintainer-email: Ulrich Schwenk <ulrich-schwenk@gmx.de>
License-File: LICENSE
Classifier: Development Status :: 5 - Production/Stable
Classifier: Intended Audience :: Information Technology
Classifier: License :: OSI Approved :: MIT License
Classifier: Operating System :: MacOS
Classifier: Operating System :: Microsoft :: Windows
Classifier: Operating System :: POSIX :: BSD
Classifier: Operating System :: POSIX :: Linux
Classifier: Programming Language :: Python :: 3.10
Classifier: Programming Language :: Python :: 3.11
Classifier: Programming Language :: Python :: 3.12
Classifier: Topic :: Communications
Classifier: Topic :: Software Development :: Libraries :: Python Modules
Classifier: Topic :: System :: Hardware
Classifier: Topic :: System :: Hardware :: Hardware Drivers
Requires-Python: >=3.10
Requires-Dist: click
Requires-Dist: hidapi
Requires-Dist: pillow
Requires-Dist: pyusb>=1.2.1
Provides-Extra: dev
Requires-Dist: black; extra == 'dev'
Requires-Dist: black[d]; extra == 'dev'
Requires-Dist: build; extra == 'dev'
Requires-Dist: coverage; extra == 'dev'
Requires-Dist: mypy; extra == 'dev'
Requires-Dist: poethepoet; extra == 'dev'
Requires-Dist: pylint; extra == 'dev'
Requires-Dist: twine; extra == 'dev'
